muse_basic_tcp_client/__init__.py
muse_basic_tcp_client/tcp_client.py
muse_basic_tcp_client-0.0.1.dist-info/METADATA
muse_basic_tcp_client-0.0.1.dist-info/WHEEL
muse_basic_tcp_client-0.0.1.dist-info/licenses/LICENSE
muse_basic_tcp_client-0.0.1.dist-info/RECORD
